Metadata-Version: 1.1
Name: jsonpyes
Version: 1.2.5
Summary: Import JSON raw data to ElasticSearch using Python in one line of commands
Home-page: https://github.com/xros/jsonpyes
Author: Alexander Liu
Author-email: UNKNOWN
License: GPL V3
Download-URL: https://github.com/xros/jsonpyes/tarball/1.2.5
Keywords: elasticsearch,json,json2es,jsonpyes
Platform: Unix
Platform: Linux
Platform: OSX
Platform: Android
Platform: Windows
